always_decimal/__init__.py
always_decimal/core.py
always_decimal-1.0.1.dist-info/METADATA
always_decimal-1.0.1.dist-info/WHEEL
always_decimal-1.0.1.dist-info/licenses/LICENSE
always_decimal-1.0.1.dist-info/RECORD
