Metadata-Version: 2.4
Name: always-decimal
Version: 1.0.1
Summary: Coerce floats/strings/Decimals to Decimal with predictable scale and rounding.
Author: Utkarsh Singh
License: MIT
License-File: LICENSE
Keywords: decimal,numeric,postgres,precision
Classifier: Programming Language :: Python :: 3 :: Only
Classifier: Programming Language :: Python :: 3.10
Classifier: Programming Language :: Python :: 3.11
Classifier: Programming Language :: Python :: 3.12
Classifier: Programming Language :: Python :: 3.13
Requires-Python: >=3.10
Provides-Extra: dev
Requires-Dist: build>=1.2; extra == 'dev'
Requires-Dist: mypy>=1.10; extra == 'dev'
Requires-Dist: pytest>=8; extra == 'dev'
Requires-Dist: ruff>=0.4; extra == 'dev'
Requires-Dist: twine>=5.1; extra == 'dev'
